{
  "level1_slug": "mechanical-aerospace-engineering",
  "level1_name": "Mechanical & Aerospace Engineering",
  "count": 48,
  "rationale": "Mechanical & Aerospace L4 splits each L3 by named application or methodology. Solid mechanics by failure regime; aerospace by system class; thermal by transport mode; manufacturing by process family; civil by structural type. 1-3 L4 per L3.",
  "leaves": [
    {"slug": "finite-deformation-plasticity", "name": "Finite Deformation Plasticity", "parent_l3": "elasticity-plasticity-finite-deformation", "tagline": "Finite deformation plasticity, crystal plasticity, large-strain modeling."},
    {"slug": "elastic-instabilities", "name": "Elastic Instabilities & Buckling", "parent_l3": "elasticity-plasticity-finite-deformation", "tagline": "Elastic instabilities, buckling, post-buckling, programmable instabilities."},
    {"slug": "ductile-brittle-fracture-mech", "name": "Ductile & Brittle Fracture", "parent_l3": "fracture-mechanics-fatigue-solid", "tagline": "Ductile + brittle fracture, ductile fracture mechanisms, hydrogen embrittlement."},
    {"slug": "fatigue-damage-tolerance", "name": "Fatigue & Damage Tolerance", "parent_l3": "fracture-mechanics-fatigue-solid", "tagline": "Fatigue + damage tolerance, very-high-cycle fatigue, AM-part fatigue."},
    {"slug": "tribology-friction-wear", "name": "Tribology, Friction & Wear", "parent_l3": "contact-multi-scale-mechanics", "tagline": "Tribology, friction + wear, contact mechanics, micro-scale tribology."},
    {"slug": "micromechanics-multiscale", "name": "Micromechanics & Multi-Scale", "parent_l3": "contact-multi-scale-mechanics", "tagline": "Micromechanics, multi-scale solid mechanics, homogenization theory."},
    {"slug": "phase-field-fem", "name": "Phase-Field & Damage FEM", "parent_l3": "computational-mechanics-fem", "tagline": "Phase-field models, damage FEM, crack propagation by phase field."},
    {"slug": "isogeometric-meshless", "name": "Isogeometric & Meshless Methods", "parent_l3": "computational-mechanics-fem", "tagline": "Isogeometric analysis, meshless methods, MPM + SPH for mechanics."},
    {"slug": "rans-les-turbulence-modeling", "name": "RANS/LES Turbulence Modeling", "parent_l3": "engineering-cfd-rans-les", "tagline": "RANS + LES turbulence modeling, hybrid RANS-LES, ML-augmented turbulence models."},
    {"slug": "hybrid-rans-les", "name": "Hybrid RANS-LES", "parent_l3": "engineering-cfd-rans-les", "tagline": "Hybrid RANS-LES (DES, IDDES, ZDES), industrial-scale turbulence simulation."},
    {"slug": "particulate-bubbly-flows", "name": "Particulate & Bubbly Flows", "parent_l3": "multiphase-flow", "tagline": "Particulate + bubbly flows, gas-liquid-solid flows, multiphase reactor flow."},
    {"slug": "droplet-microfluidics", "name": "Droplet Microfluidics", "parent_l3": "microfluidics-engineering", "tagline": "Droplet microfluidics, single-cell droplet platforms, lab-on-chip droplet engineering."},
    {"slug": "ev-aerodynamics", "name": "EV & Vehicle Aerodynamics", "parent_l3": "aero-hydrodynamics-engineering", "tagline": "EV + vehicle aerodynamics, low-drag passenger vehicle design, truck aerodynamics."},
    {"slug": "marine-hydrodynamics", "name": "Marine Hydrodynamics", "parent_l3": "aero-hydrodynamics-engineering", "tagline": "Marine hydrodynamics, hull design CFD, wave-resistance optimization."},
    {"slug": "radiative-heat-transfer", "name": "Radiative Heat Transfer", "parent_l3": "heat-conduction-convection-radiation", "tagline": "Radiative heat transfer, surface emissivity engineering, near-field radiation."},
    {"slug": "two-phase-cooling", "name": "Two-Phase Cooling", "parent_l3": "phase-change-thermal", "tagline": "Two-phase cooling, boiling enhancement, vapor-chamber cooling for electronics."},
    {"slug": "datacenter-cooling", "name": "Datacenter Thermal Management", "parent_l3": "thermal-electronics-mgmt", "tagline": "Datacenter cooling, immersion cooling, single-phase + two-phase server cooling."},
    {"slug": "ev-thermal-management", "name": "EV Thermal Management", "parent_l3": "thermal-electronics-mgmt", "tagline": "EV thermal management, battery cooling, integrated thermal architecture for EVs."},
    {"slug": "low-energy-building-hvac", "name": "Low-Energy Building HVAC", "parent_l3": "building-hvac-research", "tagline": "Low-energy building HVAC, ML for building control, advanced HVAC research."},
    {"slug": "evtol-design", "name": "eVTOL & UAM Aircraft Design", "parent_l3": "aircraft-design-aerodynamics", "tagline": "eVTOL design, urban air mobility aircraft, distributed propulsion design."},
    {"slug": "novel-config-aircraft", "name": "Novel Aircraft Configurations", "parent_l3": "aircraft-design-aerodynamics", "tagline": "Novel aircraft configurations, blended wing-body, transonic truss-braced wings."},
    {"slug": "smallsat-cubesat-design", "name": "SmallSat & CubeSat Design", "parent_l3": "spacecraft-design", "tagline": "SmallSat + CubeSat design, mission engineering for small spacecraft constellations."},
    {"slug": "deep-space-mission-design", "name": "Deep Space Mission Engineering", "parent_l3": "spacecraft-design", "tagline": "Deep space mission engineering, sample return missions, outer-planet missions."},
    {"slug": "scramjets-hypersonics", "name": "Scramjets & Hypersonic Aero", "parent_l3": "hypersonics-high-speed", "tagline": "Scramjets, hypersonic aerodynamics, high-T material engineering at hypersonic speed."},
    {"slug": "autonomous-flight-gnc", "name": "Autonomous Flight GNC", "parent_l3": "guidance-navigation-control-aero", "tagline": "Autonomous flight GNC, formation flight, learning-based aircraft GNC."},
    {"slug": "low-nox-clean-combustion", "name": "Low-NOx & Clean Combustion", "parent_l3": "combustion", "tagline": "Low-NOx + clean combustion, lean premixed combustion, hydrogen/ammonia combustion."},
    {"slug": "ic-engine-hydrogen-ammonia", "name": "Hydrogen & Ammonia IC Engines", "parent_l3": "gas-turbines-engines", "tagline": "Hydrogen + ammonia IC engines, hydrogen combustion engines, ammonia engines."},
    {"slug": "land-based-gas-turbines", "name": "Land-Based Gas Turbines", "parent_l3": "gas-turbines-engines", "tagline": "Land-based gas turbines for power generation, hydrogen-ready gas turbines."},
    {"slug": "electric-aerospace-propulsion", "name": "Electric Aerospace Propulsion", "parent_l3": "ev-hybrid-propulsion", "tagline": "Electric aerospace propulsion, hybrid-electric aircraft propulsion."},
    {"slug": "slm-laser-pbf", "name": "Laser PBF (SLM)", "parent_l3": "powder-bed-fusion-AM", "tagline": "Laser PBF, SLM, melt-pool physics in metal AM, process-microstructure for SLM."},
    {"slug": "ebm-eb-pbf", "name": "Electron-Beam PBF", "parent_l3": "powder-bed-fusion-AM", "tagline": "Electron-beam PBF, EBM, high-temperature alloy AM."},
    {"slug": "fdm-vat-photo", "name": "FDM & Vat Photopolymer AM", "parent_l3": "polymer-am-extrusion-photopolymer", "tagline": "FDM, vat photopolymer AM, DLP + SLA + CLIP printing."},
    {"slug": "in-situ-am-defects", "name": "In-Situ AM Defect Monitoring", "parent_l3": "in-situ-am-monitoring", "tagline": "In-situ AM defect monitoring, closed-loop AM control, defect detection via ML."},
    {"slug": "ultra-precision-machining", "name": "Ultra-Precision Machining", "parent_l3": "subtractive-cnc-precision", "tagline": "Ultra-precision machining, diamond turning, micro-machining."},
    {"slug": "industry-4-digital-twins", "name": "Industry 4.0 Digital Twins", "parent_l3": "smart-manufacturing-iot-mfg", "tagline": "Industry 4.0 digital twins, ML for process monitoring, smart manufacturing platforms."},
    {"slug": "performance-based-structural", "name": "Performance-Based Structural Design", "parent_l3": "structural-engineering-buildings", "tagline": "Performance-based structural design, structural reliability, seismic design optimization."},
    {"slug": "seismic-isolation-damping", "name": "Seismic Isolation & Damping", "parent_l3": "earthquake-engineering", "tagline": "Seismic isolation + damping, base-isolation systems, supplemental dampers."},
    {"slug": "ml-transportation", "name": "ML for Transportation Engineering", "parent_l3": "transportation-pavement-engineering", "tagline": "ML for transportation engineering, traffic prediction, pavement condition assessment."},
    {"slug": "geotechnical-hazards", "name": "Geotechnical Hazards & Foundation Engineering", "parent_l3": "geotechnical-engineering", "tagline": "Geotechnical hazards, foundation engineering, slope stability + liquefaction."},
    {"slug": "sustainable-cement-concrete", "name": "Sustainable Cement & Concrete", "parent_l3": "concrete-asphalt-construction-mat", "tagline": "Sustainable cement + concrete, low-carbon cement, geopolymer concrete."},
    {"slug": "self-healing-concrete", "name": "Self-Healing Concrete", "parent_l3": "smart-construction-durability", "tagline": "Self-healing concrete, smart construction materials, sensor-embedded structures."},
    {"slug": "ev-traction-vehicle-dynamics", "name": "EV Traction & Vehicle Dynamics", "parent_l3": "ev-powertrain-vehicle-dynamics", "tagline": "EV powertrain engineering, vehicle dynamics, energy management in vehicles."},
    {"slug": "av-sensor-stack-integration", "name": "AV Sensor Stack Integration", "parent_l3": "autonomous-vehicle-systems-eng", "tagline": "AV sensor stack integration, vehicle-level autonomy hardware, ADAS engineering."},
    {"slug": "soft-actuators-dielectric-elastomer", "name": "Soft Actuators & Dielectric Elastomer", "parent_l3": "soft-robotics-design", "tagline": "Soft actuators, dielectric elastomer actuators, fluidic soft actuators."},
    {"slug": "compliant-mechanisms", "name": "Compliant Mechanisms", "parent_l3": "soft-robotics-design", "tagline": "Compliant mechanisms, origami-inspired mechanisms, programmable kinematics."},
    {"slug": "exoskeletons-mech", "name": "Exoskeleton Mechanical Design", "parent_l3": "exoskeletons-prosthetics-mech", "tagline": "Exoskeleton mechanical design, gait assistance exoskeletons, industrial exoskeletons."},
    {"slug": "prosthetic-osseointegration", "name": "Prosthetic Limb & Osseointegration", "parent_l3": "exoskeletons-prosthetics-mech", "tagline": "Prosthetic limb mechanics, osseointegration, neural-prosthetic interfaces."},
    {"slug": "msk-cardiovascular-biomech", "name": "MSK & Cardiovascular Biomechanics", "parent_l3": "musculoskeletal-cardiovascular-biomech", "tagline": "MSK biomechanics, cardiovascular biomechanics, biomechanical imaging research."}
  ],
  "uncovered_concerns": [
    "Marine & Ocean Engineering papers fold under marine-hydrodynamics + EV traction L4.",
    "Design + optimization (topology, generative) folds under computational mechanics + smart manufacturing L4."
  ]
}
